httpie_bearer_auth.py
httpie_bearer_auth-1.0.0.dist-info/LICENSE
httpie_bearer_auth-1.0.0.dist-info/METADATA
httpie_bearer_auth-1.0.0.dist-info/WHEEL
httpie_bearer_auth-1.0.0.dist-info/entry_points.txt
httpie_bearer_auth-1.0.0.dist-info/top_level.txt
httpie_bearer_auth-1.0.0.dist-info/RECORD
