Metadata-Version: 2.1
Name: httpie-bearer-auth
Version: 1.0.0
Summary: Bearer token Auth plugin for HTTPie.
Home-page: https://github.com/jmsfwk/httpie-bearer-auth
Author: James Fenwick
Author-email: j.fenwick@me.com
License: MIT
Download-URL: https://github.com/jmsfwk/httpie-bearer-auth
Platform: UNKNOWN
Classifier: Development Status :: 5 - Production/Stable
Classifier: Programming Language :: Python
Classifier: Intended Audience :: Developers
Classifier: Environment :: Plugins
Classifier: License :: OSI Approved :: MIT License
Classifier: Topic :: Internet :: WWW/HTTP
Classifier: Topic :: Utilities
Requires-Dist: httpie (>=0.7.0)
